datoms.py
setup.py
datoms.egg-info/PKG-INFO
datoms.egg-info/SOURCES.txt
datoms.egg-info/dependency_links.txt
datoms.egg-info/requires.txt
datoms.egg-info/top_level.txt