Metadata-Version: 1.0
Name: datoms
Version: 0.1.0
Summary: A simplistic, Datomic inspired, SQLite backed, REST influenced, schemaless auditable facts storage.
Home-page: https://github.com/3kwa/datoms
Author: Eugene Van den Bulke
Author-email: eugene.vandenbulke@gmail.com
License: unlicense
Platform: UNKNOWN
